luhn_formula-1.0.5.dist-info/licenses/LICENSE
luhnformula/__init__.py
luhnformula/luhnformula.py
luhn_formula-1.0.5.dist-info/METADATA
luhn_formula-1.0.5.dist-info/WHEEL
luhn_formula-1.0.5.dist-info/top_level.txt
luhn_formula-1.0.5.dist-info/RECORD
