Metadata-Version: 2.4
Name: luhn-formula
Version: 1.0.5
Summary: Number validator and generator based on luhn's formula
Home-page: https://github.com/code-127/luhn-formula-py.git
Author: code-127
Author-email: 105444219+code-127@users.noreply.github.com
Project-URL: Bug Tracker, https://github.com/code-127/luhn-formula-py/issues
Classifier: Programming Language :: Python :: 3
Classifier: License :: OSI Approved :: MIT License
Classifier: Operating System :: OS Independent
Classifier: Development Status :: 5 - Production/Stable
Requires-Python: >=3.9
License-File: LICENSE
Dynamic: license-file
